nursery/__init__.py
nursery/cli.py
nursery/context.py
nursery/environment.py
nursery/pluginsystem.py
nursery/targets.py
Nursery-0.0.1a1.dist-info/METADATA
Nursery-0.0.1a1.dist-info/WHEEL
Nursery-0.0.1a1.dist-info/entry_points.txt
Nursery-0.0.1a1.dist-info/top_level.txt
Nursery-0.0.1a1.dist-info/RECORD
