Metadata-Version: 2.1
Name: Nursery
Version: 0.0.1a1
Summary: A cloud, virtual machine, and container provisioning tool
Home-page: https://github.com/terminal-labs/nursery
Author: Terminal Labs
Author-email: solutions@terminallabs.com
License: BSD
Platform: any
Classifier: Intended Audience :: Developers
Classifier: License :: OSI Approved :: BSD License
Classifier: Programming Language :: Python :: 3.8
Requires-Dist: click
Provides-Extra: test
Requires-Dist: pylint ; extra == 'test'
Requires-Dist: pytest ; extra == 'test'
Requires-Dist: pytest-cov ; extra == 'test'
Requires-Dist: pytest-mock ; extra == 'test'
Requires-Dist: pytest-click ; extra == 'test'
